STTCrypto/RepeatingXorBreaker.py
STTCrypto/__init__.py
STTCrypto/morse.py
STTCrypto/STTRSA/Arithmetic_w.py
STTCrypto/STTRSA/ContinuedFractions.py
STTCrypto/STTRSA/MillerRabin.py
STTCrypto/STTRSA/Orchestrator.py
STTCrypto/STTRSA/RSASolver.py
STTCrypto/STTRSA/RSAvulnerableKeyGenerator.py
STTCrypto/STTRSA/RSAwienerHacker.py
STTCrypto/STTRSA/__init__.py
STTCrypto/STTRSA/multiPrime.py
STTCrypto/STTRSA/x509extractor.py
STTSocket/STTSocket.py
STTSocket/__init__.py
STTUtils/StringParser.py
STTUtils/__init__.py
STTUtils/packing.py
STTUtils/utils.py
SealTeamTools-0.0.1.dist-info/LICENSE.txt
SealTeamTools-0.0.1.dist-info/METADATA
SealTeamTools-0.0.1.dist-info/WHEEL
SealTeamTools-0.0.1.dist-info/top_level.txt
SealTeamTools-0.0.1.dist-info/RECORD
