Metadata-Version: 2.1
Name: SealTeamTools
Version: 0.0.1
Summary: Collection of CTF tools (WIP)
Home-page: https://github.com/Gdasl/STT
Author: GDASL
Author-email: author@example.com
License: UNKNOWN
Platform: UNKNOWN
Classifier: Programming Language :: Python :: 3
Classifier: License :: OSI Approved :: MIT License
Classifier: Operating System :: OS Independent
Requires-Python: >=2.7
